async_btree/__init__.py
async_btree/analyze.py
async_btree/control.py
async_btree/decorator.py
async_btree/definition.py
async_btree/leaf.py
async_btree/parallele.py
async_btree/runner.py
async_btree/utils.py
async_btree-1.4.2.dist-info/METADATA
async_btree-1.4.2.dist-info/WHEEL
async_btree-1.4.2.dist-info/top_level.txt
async_btree-1.4.2.dist-info/RECORD
