Metadata-Version: 2.2
Name: async_btree
Version: 1.4.2
Summary: Async behavior tree
Author-email: Jerome Guibert <jguibert@gmail.com>
License: The MIT License (MIT)
Project-URL: homepage, https://pypi.org/project/async_btree
Project-URL: documentation, https://geronimo-iia.github.io/async-btree/
Project-URL: repository, https://github.com/geronimo-iia/async-btree
Keywords: behavior-tree,asyncio
Classifier: Development Status :: 5 - Production/Stable
Classifier: Framework :: AsyncIO
Classifier: Intended Audience :: Developers
Classifier: License :: OSI Approved :: MIT License
Classifier: Natural Language :: English
Classifier: Operating System :: OS Independent
Classifier: Programming Language :: Python
Classifier: Programming Language :: Python :: 3
Classifier: Programming Language :: Python :: 3.9
Classifier: Programming Language :: Python :: 3.11
Classifier: Programming Language :: Python :: 3.12
Classifier: Topic :: Software Development :: Libraries :: Python Modules
Classifier: Typing :: Typed
Requires-Python: <4,>=3.9
Provides-Extra: curio
Requires-Dist: curio-compat~=1.6.7; extra == "curio"
